django_cacheme/__init__.py
django_cacheme/admin.py
django_cacheme/cache_model.py
django_cacheme/models.py
django_cacheme/nodes.py
django_cacheme/utils.py
django_cacheme-0.1.3.dist-info/LICENSE
django_cacheme-0.1.3.dist-info/METADATA
django_cacheme-0.1.3.dist-info/WHEEL
django_cacheme-0.1.3.dist-info/top_level.txt
django_cacheme-0.1.3.dist-info/RECORD
